{
  "previous": "Some URL for prevoius page",
  "next": "Some URL for next page",
  "result": [
    {
      "Serial":"01",
      "Course": "CSE 246",
      "Section": "05",
      "Credit": "4.5",
      "Faculty Name": "TM",
      "Semester": "Fall24"
    },
    {
      "Serial":"02",
      "Course": "CSE 302",
      "Section": "06",
      "Credit": "4.5",
      "Faculty Name": "MRJ",
      "Semester": "Fall24"
    },{
      "Serial":"03",
      "Course": "CSE 325",
      "Section": "05",
      "Credit": "4",
      "Faculty Name": "MMHM",
      "Semester": "Fall24"
    },{
      "Serial":"05",
      "Course": "CSE 207",
      "Section": "07",
      "Credit": "4",
      "Faculty Name": "TM",
      "Semester": "Spring23"
    }
  ]
}